setup.py
timestack.py
Timestack.egg-info/PKG-INFO
Timestack.egg-info/SOURCES.txt
Timestack.egg-info/dependency_links.txt
Timestack.egg-info/top_level.txt