Metadata-Version: 1.0
Name: Timestack
Version: 0.1.0
Summary: Stack based time management tool
Home-page: https://github.com/limeburst/timestack
Author: Jihyeok Seo
Author-email: me@limeburst.net
License: UNKNOWN
Platform: UNKNOWN
